colorty/__init__.py
colorty/core.py
colorty/unix.py
colorty/util.py
colorty/windows.py
colorty/tests/__init__.py
colorty/tests/test_core.py
colorty/tests/test_unix.py
colorty/tests/test_util.py
colorty/tests/test_windows.py
colorty-0.1.6.dist-info/LICENSE
colorty-0.1.6.dist-info/METADATA
colorty-0.1.6.dist-info/WHEEL
colorty-0.1.6.dist-info/entry_points.txt
colorty-0.1.6.dist-info/top_level.txt
colorty-0.1.6.dist-info/RECORD
